hurst_fitter/__init__.py
hurst_fitter/main.py
hurst_fitter-0.0.5.dist-info/LICENSE.txt
hurst_fitter-0.0.5.dist-info/METADATA
hurst_fitter-0.0.5.dist-info/WHEEL
hurst_fitter-0.0.5.dist-info/top_level.txt
hurst_fitter-0.0.5.dist-info/RECORD
