Metadata-Version: 2.1
Name: hurst-fitter
Version: 0.0.5
Summary: Library to estimate Hurst index of time series.
Home-page: https://github.com/sauxpa/hurst_fitter
Author: Patrick Saux
Author-email: patrick.jr.saux@gmail.com
License: UNKNOWN
Platform: UNKNOWN
Requires-Python: >=3.6
Requires-Dist: numpy
Requires-Dist: scipy
Requires-Dist: pandas
Requires-Dist: statsmodels
